{
  "kind": "collectionType",
  "collectionName": "products",
  "info": {
    "singularName": "product",
    "pluralName": "products",
    "displayName": "Product",
    "description": ""
  },
  "options": {
    "draftAndPublish": true
  },
  "pluginOptions": {
    "i18n": {
      "localized": true
    }
  },
  "attributes": {
    "title": {
      "type": "string",
      "pluginOptions": {
        "i18n": {
          "localized": true
        }
      }
    },
    "description": {
      "type": "text",
      "pluginOptions": {
        "i18n": {
          "localized": true
        }
      }
    },
    "slug": {
      "type": "uid",
      "pluginOptions": {
        "i18n": {
          "localized": true
        }
      }
    },
    "sections": {
      "type": "dynamiczone",
      "pluginOptions": {
        "i18n": {
          "localized": true
        }
      },
      "components": [
        "shared.hero",
        "shared.faq",
        "shared.decision",
        "shared.card",
        "shared.card-testimonial",
        "shared.card-slim-feature",
        "shared.card-slider",
        "shared.card-simple-feature",
        "shared.card-rich-text",
        "shared.card-news",
        "shared.card-highlight",
        "shared.card-feature"
      ]
    },
    "seo": {
      "type": "component",
      "pluginOptions": {
        "i18n": {
          "localized": true
        }
      },
      "component": "shared.seo",
      "repeatable": false
    }
  }
}
